adonai_client/__init__.py
adonai_client/client.py
adonai_client/enum.py
adonai_client/exception.py
adonai_client/schema.py
adonai_client-0.1.8.dist-info/WHEEL
adonai_client-0.1.8.dist-info/METADATA
adonai_client-0.1.8.dist-info/RECORD
