Metadata-Version: 2.1
Name: adonai-client
Version: 0.1.8
Summary: Client for adonai server
License: MIT
Author: Aleksander Lavrov
Author-email: egnod@ya.ru
Requires-Python: >=3.7,<4.0
Classifier: License :: OSI Approved :: MIT License
Classifier: Programming Language :: Python :: 3
Classifier: Programming Language :: Python :: 3.7
Requires-Dist: httpx (>=0.11.1,<0.12.0)
Requires-Dist: sgqlc (>=9.1,<10.0)
